bills_combinations.py
bills_combinations-0.0.1.dist-info/LICENSE.txt
bills_combinations-0.0.1.dist-info/METADATA
bills_combinations-0.0.1.dist-info/WHEEL
bills_combinations-0.0.1.dist-info/top_level.txt
bills_combinations-0.0.1.dist-info/RECORD
