Metadata-Version: 2.1
Name: bills-combinations
Version: 0.0.1
Summary: count of possible combinations of bills in a wallet for a specific amount
License: UNKNOWN
Platform: UNKNOWN
License-File: LICENSE.txt
